nptyping/__init__.py
nptyping/assert_isinstance.py
nptyping/base_meta_classes.py
nptyping/error.py
nptyping/ndarray.py
nptyping/ndarray.pyi
nptyping/nptyping_type.py
nptyping/package_info.py
nptyping/py.typed
nptyping/recarray.py
nptyping/recarray.pyi
nptyping/shape.py
nptyping/shape.pyi
nptyping/shape_expression.py
nptyping/structure.py
nptyping/structure.pyi
nptyping/structure_expression.py
nptyping/typing_.py
nptyping/typing_.pyi
nptyping/pandas_/__init__.py
nptyping/pandas_/dataframe.py
nptyping/pandas_/dataframe.pyi
nptyping/pandas_/typing_.py
nptyping-2.5.0.dist-info/LICENSE
nptyping-2.5.0.dist-info/METADATA
nptyping-2.5.0.dist-info/WHEEL
nptyping-2.5.0.dist-info/top_level.txt
nptyping-2.5.0.dist-info/RECORD
