Metadata-Version: 2.1
Name: nptyping
Version: 2.5.0
Summary: Type hints for NumPy.
Home-page: https://github.com/ramonhagenaars/nptyping
Author: Ramon Hagenaars
Author-email: ramon.hagenaars@gmail.com
License: MIT
Platform: UNKNOWN
Classifier: Intended Audience :: Developers
Classifier: License :: OSI Approved :: MIT License
Classifier: Operating System :: OS Independent
Classifier: Natural Language :: English
Classifier: Programming Language :: Python
Classifier: Programming Language :: Python :: 3
Classifier: Programming Language :: Python :: 3.7
Classifier: Programming Language :: Python :: 3.8
Classifier: Programming Language :: Python :: 3.9
Classifier: Programming Language :: Python :: 3.10
Classifier: Programming Language :: Python :: 3.11
Requires-Python: >=3.7
Provides-Extra: build
Provides-Extra: qa
Provides-Extra: pandas
Provides-Extra: complete
Provides-Extra: dev
License-File: LICENSE
